{"Superscript":["Верхний индекс"],"Subscript":["Нижний индекс"],"Patterns":["Паттерны"],"patterns\u0004All":["Все"],"blocks\u0004Search Results":["Результаты поиска"],"Browser default":["Браузер по умолчанию"],"Left sidebar":["Область виджетов слева"],"Current theme":["Текущая тема"],"Block Library":["Библиотека блоков"],"The theme slug for the theme that created the template part.":["Ярлык для темы создавшей часть шаблона."],"Manage Locations":["Управление областями"],"Edit Navigation":["Редактировать навигацию"],"Select navigation to edit:":["Выберите навигацию для редактирования:"],"Navigation menu":["Меню навигации"],"Save navigation":["Сохранить навигацию"],"Navigation structure":["Структура навигации"],"Save the menu currently being edited.":["Сохраните редактируемое в данный момент меню."],"Block Inspector":["Инспектор блока"]," … ":["..."],"Links shown in a column.":["Ссылки, показанные в столбце."],"Navigation (vertical)":["Навигация (вертикальная)"],"Links shown in a row.":["Ссылки, показанные в строке."],"Navigation (horizontal)":["Навигация (горизонтальная)"],"Minimum height of cover":["Минимальная высота обложки"],"%1$s Block. Row %2$d":["%1$s блок. Строка %2$d"],"Typography":["Типографика"],"Line height":["Высота строки"],"Content":["Содержимое"],"Header":["Заголовок"],"Toggle fullscreen mode.":["Полноэкранный режим."],"Menu Location":["Расположение меню"],"Menu":["Меню"],"Enable Navigation screen":["Включить экран навигации"],"Navigation (beta)":["Навигация (бета)"],"Post Comments":["Комментарии к записи"],"No comments.":["Без комментариев."],"Contact":["Контакты"],"About":["Информация"],"Home":["Главная"],"25 / 50 / 25":["25 / 50 / 25"],"33 / 33 / 33":["33 / 33 / 33"],"70 / 30":["70 / 30"],"30 / 70":["30 / 70"],"50 / 50":["50 / 50"],"Current media URL:":["Текущий медиа-URL:"],"Block variations":["Вариации блока"],"Preview in new tab":["Предпросмотр в новой вкладке"],"Sort collection by object attribute.":["Сортировать коллекцию по атрибуту объекта."],"Order sort attribute ascending or descending.":["Упорядочить сортировку атрибута по возрастанию или убыванию."],"Limit result set to posts with a specific menu_order value.":["Ограничить выборку до записей с определенным значением menu_order."],"The terms assigned to the object in the %s taxonomy.":["Элементы назначенные объекту в таксономии %s."],"Whether the menu item represents an object that no longer exists.":["Представляет ли элемент меню объект, который больше не существует."],"The XFN relationship expressed in the link of this menu item.":["Отношение XFN, выраженное в ссылке этого пункта меню."],"The URL to which this menu item points.":["URL-адрес, на который указывает этот пункт меню."],"The singular label used to describe this type of menu item.":["Единственная метка, используемая для описания этого типа пункта меню."],"The target attribute of the link element for this menu item.":["Целевой атрибут элемента link для данного пункта меню."],"The DB ID of the original object this menu item represents, e . g . ID for posts and term_id for categories.":["ID в базе данных исходного объекта, который представляет этот пункт меню, например ID для записей или term_id для рубрик."],"The type of object originally represented, such as \"category,\" \"post\", or \"attachment.\"":["Тип первоначально представленного объекта, например \"category\", \"post\" или \"attachment\"."],"The DB ID of the nav_menu_item that is this item's menu parent, if any, otherwise 0.":["ID в базе данных nav_menu_item, который является родителем меню этого элемента, если таковой имеется, 0 в противном случае."],"The description of this menu item.":["Описание этого пункта меню."],"Class names for the link element of this menu item.":["Имена классов для элемента link этого пункта меню."],"Text for the title attribute of the link element for this menu item.":["Текст для атрибута title элемента link для данного пункта меню."],"A named status for the object.":["Именованный статус для объекта."],"The family of objects originally represented, such as \"post_type\" or \"taxonomy\".":["Семейство объектов, первоначально представленных, например \"post_type\" или \"taxonomy\"."],"Name of type.":["Имя типа."],"HTML title for the object, transformed for display.":["HTML название объекта, преобразованное для показа."],"Title for the object, as it exists in the database.":["Название объекта в том виде, в каком он существует в базе данных."],"Get linked object.":["Получить связанный объект."],"Invalid URL.":["Неверный URL."],"Invalid menu item parent.":["Недопустимый родительский элемент меню."],"Invalid menu position.":["Неверное положение меню."],"Invalid menu ID.":["Неверный ID меню."],"URL required if menu item of type custom.":["URL-адрес требуется, если пункт меню произвольного типа."],"Title required if menu item of type custom.":["Название требуется, если пункт меню произвольного типа."],"Invalid post ID.":["Неверный ID записи."],"The post cannot be deleted.":["Невозможно удалить запись."],"Menu items do not support trashing. Set '%s' to delete.":["Пункты меню нельзя переместить в корзину. Установите '%s' для удаления."],"Cannot create existing post.":["Невозможно создать уже имеющуюся запись."],"Sorry, you cannot view these menu items, unless you have access to permission edit them. ":["К сожалению, вы не можете просматривать эти пункты меню, если у вас нет доступа к разрешению редактировать их."],"Sorry, you are not allowed to edit posts in this post type.":["Извините, вам не разрешено редактировать записи этого типа."],"Sorry, you cannot view this menu item, unless you have access to permission edit it. ":["К сожалению, вы не можете просмотреть этот пункт меню, если у вас нет доступа к разрешению редактировать его."],"The locations assigned to the menu.":["Места, назначенные меню."],"Menu location does not exist.":["Расположение меню не существует."],"The term cannot be deleted.":["Элемент не может быть удален."],"Terms do not support trashing. Set '%s' to delete.":["Элементы нельзя переместить в корзину. Установите '%s' для удаления."],"Parent term does not exist.":["Родительского элемента не существует."],"Cannot set parent term, taxonomy is not hierarchical.":["Невозможно установить родительский термин, таксономия не является иерархической."],"Sorry, you are not allowed to assign the provided locations.":["К сожалению, вы не имеете права назначать указанные места."],"Sorry, you cannot view this menu, unless you have access to permission edit it. ":["К сожалению, вы не можете просмотреть это меню, если у вас нет доступа к разрешению редактировать его."],"Sorry, you are not allowed to edit this term.":["К сожалению, вы не можете править этот элемент."],"Sorry, you cannot view these menus, unless you have access to permission edit them. ":["К сожалению, вы не можете просматривать эти меню, если у вас нет доступа к разрешению редактировать их."],"Sorry, you are not allowed to edit terms in this taxonomy.":["Извините, вам не разрешено редактировать элементы этой таксономии."],"Pattern \"%1$s\" not found.":["Шаблон \"%1$s\" не найден."],"Pattern name must be a string.":["Имя шаблона должно быть строкой."],"The ID of the assigned menu.":["Идентификатор назначенного меню."],"The description of the menu location.":["Описание расположения меню."],"The name of the menu location.":["Имя расположения меню."],"Invalid menu location.":["Неверное расположение меню."],"Sorry, you are not allowed to view menu locations.":["К сожалению, вы не можете просматривать расположение меню."],"An alphanumeric identifier for the menu location.":["Буквенно-цифровой идентификатор расположения меню."],"Pattern \"%s\" inserted.":["Шаблон \"%s\" вставлен."],"Images size":["Размер изображений"],"User":["Пользователь"],"Widget area":["Область виджетов"],"Post Type":["Тип записи"],"Site":["Сайт"],"Move %1$s block from position %2$d left to position %3$d":["Переместить блок %1$s из позиции %2$d влево в позицию %3$d"],"Move %1$s block from position %2$d down to position %3$d":["Переместить блок %1$s из позиции %2$d вниз в позицию %3$d"],"Creating":["Создание"],"An unknown error occurred during creation. Please try again.":["Во время создания произошла неизвестная ошибка. Пожалуйста, попробуйте еще раз."],"New page: <mark>%s</mark>":["Новая страница: <mark>%s</mark>"],"Change a block's type by pressing the block icon on the toolbar.":["Измените тип блока, нажав на значок блока на панели инструментов."],"Drag files into the editor to automatically insert media blocks.":["Перетащите файлы в редактор, чтобы автоматически вставлять медиа блок."],"Outdent a list by pressing <kbd>backspace</kbd> at the beginning of a line.":["Чтобы удалить список, нажмите кнопку <kbd>backspace</kbd> в начале строки."],"Indent a list by pressing <kbd>space</kbd> at the beginning of a line.":["Сделайте отступ в списке, нажав клавишу <kbd>space</kbd> в начале строки."],"Desktop":["Настольный ПК"],"Mobile":["Мобильный"],"Tablet":["Планшет"],"Post Tags":["Метки"],"No tags.":["Меток нет."],"Post Featured Image":["Изображение записи"],"Read more…":["Читать далее…"],"Show link on new line":["Показать ссылку на новой строке"],"Max words":["Максимально слов"],"Post Excerpt Settings":["Настройки отрывка записи"],"Date Format":["Формат даты"],"Format settings":["Настройки формата"],"Change Date":["Дата изменения"],"Post Comments Form":["Форма комментирования записи"],"Post Comments Count":["Количество комментариев к записи"],"Display icons linking to your social media profiles or websites.":["Отображение значков, ссылающихся на ваши профили в социальных сетях или веб-сайты."],"Select poster image":["Выберите изображение обложки"],"Post content":["Содержимое записи"],"Background color":["Цвет фона"],"Media file":["Медиафайл"],"Text color":["Цвет текста"],"Change heading level":["Изменение уровня заголовка"],"survey":["опрос"],"social":["соцсети"],"Edit Page Template":["Редактировать шаблон страницы"],"Update Design":["Обновить дизайн"],"New":["Новый"],"Switch Template":["Переключить шаблон"],"Loading…":["Загрузка..."],"Customized":["Настраиваемый"],"template-slug":["slug-шаблона"],"Add Template":["Добавить шаблон"],"Template already exists, edit it instead.":["Шаблон уже существует, отредактируйте его вместо этого."],"Global Styles":["Глобальные стили"],"Empty template.":["Пустой шаблон."],"No matching template found.":["Соответствующие шаблоны не найдены."],"Display an icon linking to a social media profile or website.":["Отображение значка, ссылающегося на профиль в социальных сетях или веб-сайт."],"Social Icon":["Иконка соцсети"],"block keywords\u0004links":["ссылки"],"Social Icons":["Иконки соцсетей"],"Image alignment":["Выравнивание изображения"],"Display featured image":["Показывать изображение записи"],"Featured image settings":["Настройки изображения записи"],"Show submenu indicator icons":["Показывать иконки указателей подменю"],"Embed a TikTok video.":["Вставить видео TikTok."],"Block %1$s is at the beginning of the content and can’t be moved left":["Блок %1$s находится в начале содержимого и не может быть перемещен"],"Block %1$s is at the beginning of the content and can’t be moved up":["Блок %1$s находится в начале содержимого и не может быть перемещен вверх"],"Block %1$s is at the end of the content and can’t be moved left":["Блок %1$s находится в конце содержимого и не может быть перемещен"],"Block %1$s is at the end of the content and can’t be moved down":["Блок %1$s находится в конце содержимого и не может быть перемещен вниз"],"Solid":["Сплошной"],"Open document settings":["Открыть настройки документа"],"Open block settings":["Открыть настройки блока"],"Radial Gradient":["Радиальный градиент"],"Linear Gradient":["Линейный градиент"],"Type":["Тип"],"Display settings":["Показать настройки"],"Choose variation":["Выберите вариант"],"Angle":["Угол"],"%s Block":["%s Блок"],"%1$s Block. %2$s":["%1$s Блок. %2$s"],"%1$s Block. Column %2$d":["%1$s блок. Столбец %2$d"],"%1$s Block. Column %2$d. %3$s":["%1$s Блок. Столбец %2$d. %3$s"],"%1$s Block. Row %2$d. %3$s":["%1$s Блок. Строка %2$d. %3$s"],"Post Excerpt":["Выдержка"],"Post Date":["Дата записи"],"No Date":["Нет даты"],"Post Author":["Автор записи"],"Choose":["Выбрать"],"twentytwenty":["twentytwenty"],"Theme":["Тема"],"Choose a template part by slug and theme, or create a new one.":["Выберите часть шаблона по ярлыку и теме или создайте новый."],"Error adding template.":["Ошибка добавления шаблона."],"Footer label":["Ярлык подвала"],"Header label":["Ярлык заголовка"],"Unsupported":["Не поддерживается"],"The description will be displayed in the menu if the current theme supports it.":["Описание будет отображаться в меню, если текущая тема поддерживает его."],"Level %1$s. %2$s":["Уровень %1$s. %2$s"],"Level %s. Empty.":["Уровень %s. Пустой."],"Empty":["Пусто"],"Search results for \"%s\"":["Результаты поиска для %s"],"Recently updated":["Недавно обновлённые"],"Multiple selected blocks":["Несколько выбранных блоков"],"By %s":["От %s"],"Briefly describe the link to help screen reader users.":["Кратко опишите ссылку, чтобы помочь пользователям с программой чтения с экрана."],"Link label":["Ярлык ссылки"],"%s label":["%s ярлык"],"poem":["стих"],"Matt Mullenweg":["Matt Mullenweg"],"EXT. XANADU - FAINT DAWN - 1940 (MINIATURE)\nWindow, very small in the distance, illuminated.\nAll around this is an almost totally black screen. Now, as the camera moves slowly towards the window which is almost a postage stamp in the frame, other forms appear;":["EXT. XANADU - FAINT DAWN - 1940 (MINIATURE)\nОкно,очень маленькое вдалеке, освещено.\nВсе вокруг - это почти полностью черный экран. Теперь, когда камера медленно движется к окну, которое является почти почтовой маркой в кадре, появляются другие формы;"],"Full post":["Полная запись"],"Show:":["Показать:"],"Create from all top-level pages":["Создать из всех страниц верхнего уровня"],"Suspendisse commodo neque lacus, a dictum orci interdum et.":["Suspendisse commodo neque lacus, a dictum orci interdum et."],"Lorem ipsum dolor sit amet, consectetur adipiscing elit. Praesent et eros eu felis.":["Lorem ipsum dolor sit amet, consectetur adipiscing elit. Praesent et eros eu felis."],"Prompt visitors to take action with a group of button-style links.":["Побудите посетителей к действию с помощью группы ссылок в стиле кнопок."],"Buttons":["Кнопки"],"Image size":["Размер изображения"],"Remove multiple selected blocks.":["Удалите несколько выбранных блоков."],"(%s: gradient %s)":["(%s: градиент %s)"],"(%s: color %s)":["(%s: цвет %s)"],"(Gradient: %s)":["(Градиент: %s)"],"(Color: %s)":["(Цвет: %s)"],"Here's a detailed guide.":["Вот вам подробное руководство."],"New to the block editor? Want to learn more about using it? ":["Новичок в Редакторе блоков? Хотите узнать больше о его использовании?"],"Learn how to use the block editor":["Узнайте, как использовать Редактор блоков"],"Help":["Помощь"],"https://wordpress.org/support/article/wordpress-editor/":["https://wordpress.org/support/article/wordpress-editor/"],"%s block icon":["%s иконка блока"],"Submit for Review…":["Отправить на рассмотрение..."],"Update…":["Обновление..."],"Select items to save.":["Выберите элементы для сохранения."],"What do you want to save?":["Что вы хотите сохранить?"],"Untitled":["Без заголовка"],"The block editor includes experimental features that are useable while they're in development. Select the ones you'd like to enable. These features are likely to change, so avoid using them in production.":["Редактор блоков включает в себя экспериментальные функции, которые можно использовать в процессе разработки. Выберите те, которые вы хотите включить. Эти функции, скорее всего, изменятся, поэтому избегайте их использования на рабочем сайте."],"Enable Full Site Editing (Warning: this will replace your theme and cause potentially irreversible changes to your site. We recommend using this only in a development environment.)":["Включите полное редактирование сайта (Предупреждение: это заменит вашу тему и приведет к потенциально необратимым изменениям на вашем сайте. Мы рекомендуем использовать это только в среде разработки.)"],"Site Editor (beta)":["Редактор сайта (бета)"],"// A \"block\" is the abstract term used\n// to describe units of markup that\n// when composed together, form the\n// content or layout of a page.\nregisterBlockType( name, settings );":["// \"Блок\" - это абстрактный термин, используемый\n// для описания единиц разметки, которые\n// совместно, формируют\n// контент или макет страницы.\nregisterBlockType( name, settings );"],"You are probably offline.":["Вы, вероятно, не в сети."],"Justify items right":["Выравнивание элементов справа"],"Justify items center":["Выравнивание элементов по центру"],"Justify items left":["Выравнивание элементов слева"],"Change items justification":["Изменить выравнивание элементов"],"The media file has been replaced":["Медиафайл был заменён"],"Replace":["Заменить"],"You are currently in edit mode. To return to the navigation mode, press Escape.":["В настоящее время вы находитесь в режиме редактирования. Чтобы вернуться в режим навигации, нажмите клавишу Escape."],"You are currently in navigation mode. Navigate blocks using the Tab key. To exit navigation mode and edit the selected block, press Enter.":["В данный момент Вы находитесь в режиме навигации. Навигация по блокам осуществляется с помощью клавиши Tab. Для выхода из режима навигации и редактирования выбранного блока нажмите клавишу Enter."],"Use your left or right arrow keys or drag and drop with the mouse to change the gradient position. Press the button to change the color or remove the control point.":["Используйте клавиши со стрелками влево или вправо или перетащите с помощью мыши, чтобы изменить положение градиента. Нажмите кнопку, чтобы изменить цвет или удалить контрольную точку."],"Gradient control point at position %1$s with color code %2$s.":["Контрольная точка градиента в позиции %1$s с кодом цвета %2$s."],"Preset size":["Установить размер"],"Tools offer different interactions for block selection & editing. To select, press Escape, to go back to editing, press Enter.":["Инструменты предлагают различные взаимодействия для выбора и редактирования блоков. Чтобы выбрать - нажмите Escape, чтобы вернуться к редактированию - нажмите Enter."],"Open Media Library":["Открыть библиотеку файлов"],"Next":["Вперёд"],"Previous":["Назад"],"Finish":["Готово"],"Page %1$d of %2$d":["Страница %1$d из %2$d"],"Guide controls":["Управление инструкцией"],"Remove Control Point":["Удалить контрольную точку"],"Each block comes with its own set of controls for changing things like color, width, and alignment. These will show and hide automatically when you have a block selected.":["У каждого блока есть свой собственный набор элементов управления для изменения цвета, ширины, выравнивания и других настроек. Они будут отображаться при выборе блока."],"Make each block your own":["Сделайте каждый блок собственным"],"In the WordPress editor, each paragraph, image, or video is presented as a distinct “block” of content.":["В редакторе WordPress каждый абзац, изображение или видео представлены в виде отдельного \"блока\" содержимого."],"ADD MEDIA":["ДОБАВИТЬ МЕДИА"],"All of the blocks available to you live in the block library. You’ll find it wherever you see the <InserterIconImage /> icon.":["Все доступные вам блоки находятся в библиотеке блоков. Вы найдёте её везде, где видите <InserterIconImage /> иконку."],"Get to know the block library":["Познакомьтесь с библиотекой блоков"],"Welcome Guide":["Начальная инструкция"],"Enable Full Site Editing demo templates":["Включить полное редактирование сайта демо-шаблоны"],"Full Site Editing Demo Templates":["Полное редактирование сайта демо-шаблоны"],"Welcome to the block editor":["Добро пожаловать в Редактор блоков"],"Get started":["Начало работы"],"inserter":["Вставка"],"Post Title":["Заголовок записи"],"Add nofollow to link":["Добавить nofollow в ссылку"],"Add submenu":["Добавить подменю"],"Add link…":["Добавить ссылку..."],"Dark":["Тёмный"],"Light":["Светлый"],"recording":["запись"],"podcast":["подкаст"],"sound":["звук"],"Array of instance changes":["Массив изменений экземпляра"],"Current widget instance":["Текущий экземпляр виджета"],"Template parts to include in your templates.":["Части шаблона для включения в ваши шаблоны."],"Template parts list":["Список частей шаблона"],"Template parts list navigation":["Навигация по списку частей шаблона"],"Filter template parts list":["Фильтр списка частей шаблона"],"Uploaded to this template part":["Загружено в эту часть шаблона"],"Insert into template part":["Вставить в часть шаблона"],"Template part archives":["Архивы частей шаблона"],"No template parts found in Trash.":["В корзине нет частей шаблона."],"No template parts found.":["Частей шаблона не найдено."],"Parent Template Part:":["Родительская часть шаблона:"],"Search Template Parts":["Поиск частей шаблона"],"All Template Parts":["Все части шаблона"],"View Template Part":["Просмотр части шаблона"],"Edit Template Part":["Изменить часть шаблона"],"New Template Part":["Новая часть шаблона"],"Add New Template Part":["Добавить новую часть шаблона"],"Template Part\u0004Add New":["Добавить новый"],"Admin Menu text\u0004Template Parts":["Части шаблона"],"Template Part":["Часть шаблона"],"Template Parts":["Части шаблона"],"WHAT was he doing, the great god Pan,\n\tDown in the reeds by the river?\nSpreading ruin and scattering ban,\nSplashing and paddling with hoofs of a goat,\nAnd breaking the golden lilies afloat\n    With the dragon-fly on the river.":["Над чем развозился великий бог Пан,\nВнизу в камышах на реке?\nНаносит повсюду разор да изъян,\nПлескаясь и брызжа козлиной ногой,\nКувшинкам помял он убор золотой,\nСтрекоз разогнал по реке."],"Menu Item":["Элемент меню"],"Navigation":["Навигация"],"Loading Navigation…":["Загрузка навигации…"],"Navigation Structure":["Структура навигации"],"Create empty":["Создать пустой"],"Create a Navigation from all existing pages, or create an empty one.":["Создайте навигацию из всех существующих страниц или создайте пустую."],"Navigation Link":["Ссылка навигации"],"(Note: many devices and browsers do not display this text.)":["(Примечание: многие устройства и браузеры не отображают этот текст.)"],"Describe the role of this image on the page.":["Опишите роль этого изображения на странице."],"Toggle between using the same value for all screen sizes or using a unique value per screen size.":["Переключение между использованием одного и того же значения для всех размеров экрана или с использованием уникального значения для каждого размера экрана."],"Use the same %s on all screensizes.":["Используйте один и тот же %s на всех экранах."],"Large screens":["Большие экраны"],"Medium screens":["Средние экраны"],"Small screens":["Маленькие экраны"],"Text labelling a interface as controlling a given layout property (eg: margin) for a given screen size.\u0004Controls the %1$s property for %2$s viewports.":["Управляет свойством %1$s для %2$s области просмотра."],"Currently selected":["В настоящее время выбрано"],"Search or type url":["Введите поисковый запрос или URL"],"Press ENTER to add this link":["Нажмите кнопку ENTER, чтобы добавить эту ссылку"],"Currently selected link settings":["Текущие настройки выбранной ссылки"],"Generic label for block inserter button\u0004Add block":["Добавить блок"],"directly add the only allowed block\u0004Add %s":["Добавить %s"],"%s block added":["%s блок добавлен"],"Extra Large":["Очень крупный"],"Block breadcrumb":["Блок хлебных крошек"],"Site Title":["Название сайта"],"Open Colors Selector":["Открыть выбор цвета"],"Templates list":["Список шаблонов"],"Templates list navigation":["Навигация по списку шаблонов"],"Filter templates list":["Фильтр списка шаблонов"],"Uploaded to this template":["Загружено в этот шаблон"],"Insert into template":["Вставить в шаблон"],"Template archives":["Архивы шаблонов"],"No templates found in Trash.":["Нет шаблонов в корзине."],"No templates found.":["Шаблоны не найдены."],"Parent Template:":["Родительский шаблон:"],"Search Templates":["Поиск шаблонов"],"All Templates":["Все шаблоны"],"View Template":["Просмотреть шаблон"],"Edit Template":["Изменить шаблон"],"New Template":["Новый шаблон"],"Add New Template":["Добавить новый шаблон"],"Template\u0004Add New":["Добавить новый"],"Admin Menu text\u0004Templates":["Шаблоны"],"Template":["Шаблон"],"No matching template found":["Соответствующие шаблоны не найдены."],"Gradient: %s":["Градиент: %s"],"Gradient code: %s":["Код градиента: %s"],"All content copied.":["Всё содержимое было скопировано."],"Media upload failed. If this is a photo or a large image, please scale it down and try again.":["Загрузка медиафайла не удалась. Если это фотография или изображение большого размера, уменьшите его и попробуйте снова."],"Gradient":["Градиент"],"Gradient Presets":["Настройки градиента"],"No Preview Available.":["Предварительный просмотр недоступен."],"Midnight":["Полуночный"],"Electric grass":["Электрическая трава"],"Pale ocean":["Бледный океан"],"Luminous dusk":["Светящиеся сумерки"],"Blush bordeaux":["Пурпурно-красный"],"Blush light purple":["Пастельный светло-фиолетовый"],"Cool to warm spectrum":["Холодный к тёплому спектру"],"Very light gray to cyan bluish gray":["Светло-серый к голубовато-серому"],"Luminous vivid orange to vivid red":["Ярко-оранжевый к ярко-красному"],"Luminous vivid amber to luminous vivid orange":["Янтарный к ярко-оранжевому"],"Light green cyan to vivid green cyan":["Светло-зеленый к ярко-зелёному"],"Vivid cyan blue to vivid purple":["Ярко-синий к ярко-фиолетовому"],"https://wordpress.org/support/article/excerpt/":["https://ru.wordpress.org/support/article/excerpt/"],"December 6, 2018":["6 декабря 2018"],"February 21, 2019":["21 февраля 2019"],"May 7, 2019":["7 мая 2019"],"Release Date":["Дата выхода"],"Jazz Musician":["Джазовый музыкант"],"Version":["Версия"],"Six.":["Шесть."],"Five.":["Пять."],"Four.":["Четыре."],"Three.":["Три."],"Two.":["Два."],"One.":["Один."],"One of the hardest things to do in technology is disrupt yourself.":["One of the hardest things to do in technology is disrupt yourself."],"— Kobayashi Issa (一茶)":[" — Кобаяси Исса (一茶)"],"The wren<br>Earns his living<br>Noiselessly.":["Клюв свой раскрыв,<br>Запеть не успел крапивник.<br>Кончился день."],"Welcome to the wonderful world of blocks…":["Добро пожаловать в удивительный мир блоков..."],"<strong>Snow Patrol</strong>":["<strong>Снежный патруль</strong>"],"Dimensions":["Размеры"],"Nam risus massa, ullamcorper consectetur eros fermentum, porta aliquet ligula. Sed vel mauris nec enim.":["Nam risus massa, ullamcorper consectetur eros fermentum, porta aliquet ligula. Sed vel mauris nec enim."],"Etiam et egestas lorem. Vivamus sagittis sit amet dolor quis lobortis. Integer sed fermentum arcu, id vulputate lacus. Etiam fermentum sem eu quam hendrerit.":["Etiam et egestas lorem. Vivamus sagittis sit amet dolor quis lobortis. Integer sed fermentum arcu, id vulputate lacus. Etiam fermentum sem eu quam hendrerit."],"Call to Action":["Призыв к действию"],"In quoting others, we cite ourselves.":["Цитируя других, мы цитируем себя."],"cite":["цитировать"],"Mont Blanc appears—still, snowy, and serene.":["Mont Blanc appears—still, snowy, and serene."],"In a village of La Mancha, the name of which I have no desire to call to mind, there lived not long since one of those gentlemen that keep a lance in the lance-rack, an old buckler, a lean hack, and a greyhound for coursing.":["В скромной деревушке провинции Ламанчи жил идальго, по имени Дон Кехана. Как и всякий дворянин, он гордился своим благородным происхождением, свято хранил древний щит и родовое копье и держал у себя на дворе тощую клячу и борзую собаку."],"Block navigation":["Навигация по блокам"],"Full Site Editing":["Полное редактирование сайта"],"Templates to include in your theme.":["Шаблоны для включения в вашу тему."],"Templates":["Шаблоны"],"Pre-publish checks":["Проверки перед публикацией"],"Please contact your site administrator to install new blocks.":["Для установки новых блоков обратитесь к администратору сайта."],"No blocks found in your library. Please contact your site administrator to install new blocks.":["В вашей библиотеке нет блоков. Для установки новых блоков обратитесь к администратору сайта."],"No blocks found in your library.":["В вашей библиотеке нет блоков."],"No blocks found in your library. These blocks can be downloaded and installed:":["В вашей библиотеке нет блоков. Эти блоки можно скачать и установить:"],"No blocks found in your library. We did find %d block available for download.":["В вашей библиотеке нет блоков. Мы нашли %d блок, доступный для загрузки.","В вашей библиотеке нет блоков. Мы нашли %d блока, доступных для загрузки.","В вашей библиотеке нет блоков. Мы нашли %d блоков, доступных для загрузки."],"Block previews can’t load.":["Предпросмотр блока не загружается."],"Retry":["Повторить"],"Block previews can't install.":["Не удается установить предпросмотр блока."],"Updated %s":["Обновлено %s"],"%d active installation":["%d активная установка","%d активных установки","%d активных установок"],"This author has %1$d block, with an average rating of %2$d.":["Этот автор имеет %1$d блок, со средним рейтингом %2$d.","Этот автор имеет %1$d блока, со средним рейтингом %2$d.","Этот автор имеет %1$d блоков, со средним рейтингом %2$d."],"Authored by %s":["Предоставленные %s"],"Add":["Добавить"],"%d total rating":["%d всего оценка","%d всего оценки","%d всего оценок"],"%s out of 5 stars":["%s из 5 звёзд"],"Enter address":["Введите адрес"],"Pill Shape":["Форма таблетки"],"Logos Only":["Только логотипы"],"Open block navigator":["Навигация по открытым блокам"],"Attachment page":["Страница вложения"],"Fill":["Заполнить"],"Link rel":["rel ссылки"],"Border radius":["Закругление углов"],"Write gallery caption…":["Написать заголовок галереи…"],"Restore the backup":["Восстановить из резервной копии"],"The backup of this post in your browser is different from the version below.":["Резервная копия этой записи в вашем браузере отличается от версии ниже."],"Enable block directory search":["Включить поиск в каталоге блоков"],"Block Directory":["Каталог блоков"],"Unable to connect to the filesystem. Please confirm your credentials.":["Не удалось подключиться к файловой системе. Пожалуйста, подтвердите свои учетные данные."],"Sorry, you are not allowed to install blocks.":["К сожалению, вы не можете установить блоки."],"%d block is disabled.":["%d блок отключен.","%d блока отключено.","%d блоков отключено."],"Reverse list numbering":["Обратная нумерация списка"],"Start value":["Начальное значение"],"Ordered list settings":["Настройки упорядоченного списка"],"Clear Media":["Очистить медиа"],"Default Style":["Стиль по умолчанию"],"Not set":["Не установлен"],"While writing, you can press <kbd>/</kbd> to quickly insert new blocks.":["Во время написания, вы можете нажать <kbd>/</kbd>, чтобы быстро вставить новые блоки."],"Version of the content block format used by the object.":["Версия формата блоков содержимого, используемая объектом."],"HTML content for the object, transformed for display.":["HTML содержимое для объекта, преобразованное для показа."],"Content for the object, as it exists in the database.":["Содержимое для объекта, как оно существует в базе данных."],"The content for the object.":["Содержимое для объекта."],"Change column alignment":["Изменить выравнивание столбца"],"Align Column Right":["Выровнять столбец справа"],"Align Column Center":["Выровнять столбец по центру"],"Align Column Left":["Выровнять столбец слева"],"Color":["Цвет"],"Vivid purple":["яркий фиолетовый"],"Disable & Reload":["Отключить и перезагрузить"],"Enable & Reload":["Включить и перезагрузить"],"A page reload is required for this change. Make sure your content is saved before reloading.":["Для этого изменения требуется перезагрузить страницу. Убедитесь в том, что вы сохранили содержимое перед перезагрузкой."],"Display these keyboard shortcuts.":["Показывать эти горячие клавиши"],"Experiments Settings":["Экспериментальные настройки"],"Enable Widgets screen and Legacy Widgets block":["Включить экран виджетов и блок старых виджетов"],"Experimental settings":["Экспериментальные настройки"],"Block name name must be a string.":["Имя блока должно быть строкой."],"Custom":["Произвольный"],"Draft":["Черновик"],"Block \"%1$s\" does not contain a style named \"%2$s.\".":["Блок \"%1$s\" не содержит стиля с именем \"%2$s.\"."],"Learn more about anchors":["Узнайте больше об якорях"],"Enter a word or two — without spaces — to make a unique web address just for this heading, called an “anchor.” Then, you’ll be able to link directly to this section of your page.":["Введите слово или два - без пробелов - чтобы создать уникальный веб-адрес только для этого заголовка, который называется “якорь“. Затем вы сможете напрямую ссылаться на этот раздел своей страницы."],"Widget Blocks (Experimental)":["Блоки виджетов (Экспериментальное)"],"Upload a video file, pick one from your media library, or add one with a URL.":["Загрузите видеофайл, выберите его из медиабиблиотеки или добавьте URL-адрес."],"Upload an image file, pick one from your media library, or add one with a URL.":["Загрузите файл изображения, выберите из медиабиблиотеки или добавьте URL-адрес."],"Upload an audio file, pick one from your media library, or add one with a URL.":["Загрузите аудиофайл, выберите его из медиабиблиотеки или добавьте URL-адрес."],"Upload a media file or pick one from your media library.":["Загрузите медиафайл или выберите его из медиабиблиотеки."],"Skip":["Пропустить"],"Select a variation to start with.":["Выберите вариант для начала."],"Add a page, link, or another item to your navigation.":["Добавьте страницу, ссылку или другой элемент в навигацию."],"What's this?":["Что это?"],"https://codex.wordpress.org/Nofollow":["https://codex.wordpress.org/Nofollow"],"Don't let search engines follow this link.":["Не позволяет поисковым системам переходить по этой ссылке."],"Title attribute":["Атрибут title"],"SEO settings":["Настройки СЕО"],"Description":["Описание"],"Open in new tab":["Открыть в новой вкладке"],"Move right":["Переместить вправо"],"Move left":["Переместить влево"],"links":["ссылки"],"navigation":["навигация"],"menu":["меню"],"Add a navigation block to your site.":["Добавьте блок навигации на свой сайт."],"Upload a file or pick one from your media library.":["Загрузите файл или выберите его из медиабиблиотеки."],"Learn more about embeds":["Узнайте больше о встраиваниях"],"https://wordpress.org/support/article/embeds/":["https://codex.wordpress.org/Вставка_объектов"],"Paste a link to the content you want to display on your site.":["Вставьте ссылку на контент, который вы хотите отобразить на своем сайте."],"Upload an image or video file, or pick one from your media library.":["Загрузите изображение или видеофайл или выберите его из медиабиблиотеки."],"Three columns; wide center column":["Три колонки; широкая центральная колонка"],"Three columns; equal split":["Три колонки; равное разделение"],"Two columns; two-thirds, one-third split":["Две колонки; две трети, одна треть разделение"],"Two columns; one-third, two-thirds split":["Две колонки; одна треть, две трети разделение"],"Two columns; equal split":["Две колонки; равное разделение"],"Your site doesn&#8217;t have any %s, so there&#8217;s nothing to display here at the moment.":["На вашем сайте нет %s, поэтому здесь нечего показывать."],"More tools & options":["Больше инструментов и возможностей"],"Create Table":["Создать таблицу"],"Insert a table for sharing data.":["Создать таблицу для представления данных."],"Ungrouping blocks from within a Group block back into individual blocks within the Editor \u0004Ungroup":["Разгруппировать"],"verb\u0004Group":["Группировать"],"Separate with commas or the Enter key.":["Разделяйте запятыми или клавишей Enter."],"Separate with commas, spaces, or the Enter key.":["Разделяйте запятыми, пробелами или клавишей Enter."],"Separate multiple classes with spaces.":["Разделите несколько классов пробелами."],"Move image forward":["Переместить изображение вперёд"],"Move image backward":["Переместить изображение назад"],"Sorry, you are not allowed to edit sidebars.":["К сожалению, вы не можете редактировать области виджетов."],"Sorry, you are not allowed to read sidebars.":["К сожалению, вы не можете читать области виджетов."],"The sidebar’s ID.":["ID области виджетов."],"Displays a set of blocks":["Отображает набор блоков"],"Blocks Area":["Область блоков"],"Block rendered as empty.":["Блок отображается как пустой."],"Inline Code":["Встроенный код"],"Note: Autoplaying videos may cause usability issues for some visitors.":["Заметка: Автоматическое воспроизведение видео может вызвать проблемы с использованием у некоторых посетителей."],"Footer section":["Область подвала"],"Header section":["Область заголовка"],"Sorting and filtering":["Сортировка и фильтрация"],"Post meta settings":["Настройки метаданных записи"],"Post Content":["Содержимое записи"],"Post content settings":["Настройки содержимого записи"],"Percentage width":["Ширина в процентах"],"Column settings":["Настройки столбца"],"Note: Autoplaying audio may cause usability issues for some visitors.":["Заметка: Автоматическое воспроизведение звука может вызвать проблемы с использованием у некоторых посетителей."],"Block area updated.":["Область блоков обновлена."],"Block area scheduled.":["Область блоков запланирована к публикации."],"Block area published.":["Область блоков опубликована."],"Block areas list":["Список областей блоков"],"Block areas list navigation":["Навигация по списку областей блоков"],"Filter block areas list":["Отфильтровать список областей блоков"],"No block area found.":["Область блоков не найдена."],"Search Block Areas":["Поиск областей блоков"],"All Block Areas":["Все области блоков"],"View Block Area":["Посмотреть область блоков"],"Edit Block Area":["Изменить область блоков"],"New Block Area":["Новая область блоков"],"Add New Block Area":["Добавить новую область блоков"],"admin menu\u0004Block Areas":["Области блоков"],"post type singular name\u0004Block Area (Experimental)":["Область блоков (Экспериментальное)"],"post type general name\u0004Block Area (Experimental)":["Область блоков (Экспериментальное)"],"Experimental custom post type that will store block areas referenced by themes.":["Экспериментальный пользовательский тип записи, сохраняющий области блоков, на которые ссылаются темы."],"Widgets screen content":["Содержимое экрана виджетов"],"header":["заголовок"],"Footer":["Подвал"],"(experimental)":["(экспериментальный)"],"Block Areas":["Области Блока"],"This color combination may be hard for people to read.":["Это сочетание цветов может быть трудным для чтения людьми."],"There is no poster image currently selected":["В данный момент изображение постера не выбрано"],"The current poster image url is %s":["Текущий URL изображения постера %s"],"section":["раздел"],"row":["строка"],"wrapper":["обёртка"],"container":["контейнер"],"A block that groups other blocks.":["Блок, который группирует другие блоки."],"Group":["Группа"],"Crop image to fill entire column":["Обрезать изображение для заполнения всего столбца"],"Play inline":["Воспроизводить встроенным"],"Leave empty if the image is purely decorative.":["Оставьте пустым, если изображение чисто декоративное."],"Describe the purpose of the image":["Опишите назначение изображения"],"Add a block":["Добавить блок"],"Block vertical alignment setting label\u0004Change vertical alignment":["Изменить вертикальное выравнивание"],"Block vertical alignment setting\u0004Vertically Align Bottom":["Вертикальное выравнивание вниз"],"Block vertical alignment setting\u0004Vertically Align Middle":["Вертикальное выравнивание по центру"],"Replace Image":["Заменить изображение"],"Block vertical alignment setting\u0004Vertically Align Top":["Вертикальное выравнивание вверх"],"Display a legacy widget.":["Показать устаревший виджет."],"Legacy Widget (Experimental)":["Устаревший виджет (Экспериментальное)"],"Change widget":["Изменить виджет"],"Legacy Widget":["Устаревший виджет"],"You don't have permissions to use widgets on this site.":["У вас нет прав на использование виджетов на этом сайте."],"Select a legacy widget to display:":["Выберите устаревший виджет для отображения:"],"There are no widgets available.":["Нет доступных виджетов."],"Change block type or style":["Изменить тип блока или стиль"],"keyboard key\u0004Space":["Пробел"],"keyboard key\u0004Backspace":["Backspace"],"More rich text controls":["Больше элементов управления Rich Text"],"Search Terms":["Условия поиска"],"Exit the Editor":["Выход из редактора"],"Block Manager":["Менеджер блоков"],"Class name of the widget.":["Имя класса виджета."],"Sorry, you are not allowed to access widgets on this site.":["Извините, у вас нет доступа к виджетам на этом сайте."],"Widgets (beta)":["Виджеты (бета)"],"link":["ссылка"],"Embedded content from %s can't be previewed in the editor.":["Встроенное содержимое из %s невозможно просмотреть в редакторе."],"Custom color":["Произвольный цвет"],"Prompt visitors to take action with a button-style link.":["Мотивируйте посетителей к действию ссылкой в виде кнопки."],"Stick to the top of the blog":["Прилепить к верхней части блога"],"Read about permalinks":["Читайте о постоянных ссылках"],"The last part of the URL.":["Последняя часть URL."],"URL Slug":["Ярлык URL"],"A cloud of your most used tags.":["Облако часто используемых меток."],"Tag Cloud":["Облако меток"],"Taxonomy":["Таксономия"],"Tag Cloud settings":["Настройки облака меток"],"- Select -":["- Выбрать -"],"Default":["По умолчанию"],"find":["Найти"],"Help visitors find your content.":["Помогите посетителям найти ваше содержимое."],"Search":["Поиск"],"Add button text…":["Добавить текст кнопки..."],"Button text":["Текст кнопки"],"Optional placeholder…":["Необязательный заполнитель…"],"Optional placeholder text":["Текст необязательного заполнителя"],"Add label…":["Добавить пометку..."],"Label text":["Текст лейбла"],"image %1$d of %2$d in gallery":["изображение %1$d из %2$d в галерее"],"archive":["архив"],"posts":["записи"],"A calendar of your site’s posts.":["Календарь записей вашего сайта."],"Calendar":["Календарь"],"by":["от"],"An error has occurred, which probably means the feed is down. Try again later.":["Произошла ошибка, которая, вероятно, означает, что канал не работает. Повторите попытку позже."],"RSS Error:":["Ошибка RSS:"],"block style\u0004Default":["По умолчанию"],"Fullscreen mode deactivated":["Полноэкранный режим отключен"],"Fullscreen mode activated":["Полноэкранный режим включен"],"Spotlight mode deactivated":["Режим подсветки деактивирован"],"Spotlight mode activated":["Режим подсветки активирован"],"Top toolbar deactivated":["Верхняя панель инструментов отключена"],"Top toolbar activated":["Верхняя панель инструментов включена"],"Back":["Назад"],"Feature activated":["Возможность активирована"],"Feature deactivated":["Возможность деактивирована"],"Vertical pos.":["Вертикальная позиция"],"Horizontal pos.":["Горизонтальная позиция"],"feed":["RSS-лента"],"atom":["atom"],"Display entries from any RSS or Atom feed.":["Отображение записей из любой RSS-ленты или Atom."],"RSS":["RSS"],"Max number of words in excerpt":["Максимальное количество слов в отрывке"],"Display excerpt":["Показать отрывок"],"Display date":["Показать дату"],"Display author":["Показать автора"],"RSS settings":["Настройки RSS"],"Edit RSS URL":["Изменить RSS URL"],"Content before this block will be shown in the excerpt on your archives page.":["Содержимое перед этим блоком будет показано в отрывке на странице архивов."],"Hide the excerpt on the full content page":["Скрыть отрывок на странице полного содержимого"],"The excerpt is visible.":["Отрывок показан."],"The excerpt is hidden.":["Отрывок скрыт."],"Sorry, this content could not be embedded.":["Извините, это содержимое не может быть встроено."],"Embed Amazon Kindle content.":["Вставить содержимое Amazon Kindle."],"ebook":["ebook"],"Embed Crowdsignal (formerly Polldaddy) content.":["Вставить содержимое Crowdsignal (ранее Polldaddy)."],"Focal point picker":["Выбор точки фокусировки"],"Underline":["Подчеркивание"],"Attempt Block Recovery":["Попытка восстановления блока"],"Word count type. Do not translate!\u0004words":["words"],"content placeholder\u0004Content…":["Содержимое..."],"button label\u0004Convert to link":["Сконвертировать в ссылку"],"button label\u0004Try again":["Попробовать снова"],"Editor tips":["Советы по использованию редактора"],"Block (selected)":["Блок (выбран)"],"Document (selected)":["Документ (выбран)"],"CSS Font Family for Editor Font\u0004Noto Serif":["Noto Serif"],"%d word":["%d слово","%d слова","%d слов"],"Top toolbar":["Верхняя панель инструментов"],"Link Rel":["Link Rel"],"Link CSS Class":["CSS класс ссылки"],"To edit the featured image, you need permission to upload media.":["Для редактирования изображения записи вам требуется разрешение на загрузку медиафайлов."],"To edit this block, you need permission to upload media.":["Для редактирования этого блока вам требуется разрешение на загрузку медиафайлов."],"(selected block)":["(выбранный блок)"],"Block tools":["Инструменты блоков"],"Permalink":["Постоянная ссылка"],"This image has an empty alt attribute":["Это изображение имеет пустой атрибут alt"],"This image has an empty alt attribute; its file name is %s":["Это изображение имеет пустой атрибут alt; его имя файла - %s"],"Block area reverted to draft.":["Область блоков возвращена в черновики."],"Block area published privately.":["Область блоков опубликована как личная."],"No block areas found in Trash.":["Нет областей блоков в корзине."],"Block\u0004Add New":["Добавить новый"],"add new on admin bar\u0004Block Area":["Область блоков"],"Link inserted.":["Ссылка вставлена."],"Warning: the link has been inserted but may have errors. Please test it.":["Предупреждение: Ссылка вставлена, но возможно с ошибками. Пожалуйста, проверьте её."],"%s block selected.":["Выбран %s блок.","Выбраны %s блока.","Выбраны %s блоков."],"Thumbnail":["Миниатюра"],"Full Size":["Полноразмерный"],"Link selected.":["Выбрана ссылка."],"Start writing with text or HTML":["Начните писать текст или HTML-код"],"Type text or HTML":["Напишите текст или HTML-код"],"Block icon":["Значок блока"],"Align text right":["Выравнять текст по правому краю"],"Align text center":["Выравнять текст по центру"],"Align text left":["Выравнять текст по левому краю"],"Start writing or type / to choose a block":["Начните писать или нажмите / для выбора блока"],"Empty block; start writing or type forward slash to choose a block":["Пустой блок; начните писать или нажмите прямой слэш (/) для выбора блока"],"Paragraph block":["Блок параграфа"],"Page Break":["Разрыв страницы"],"Stack on mobile":["Группировать друг над другом на мобильных устройствах"],"Annotation":["Примечание"],"Drag images, upload new ones or select files from your library.":["Перетащите изображения, загрузите новые или выберите имеющиеся из медиатеки."],"blocks\u0004Most used":["Часто используемые"],"imperative verb\u0004Resolve":["Исправить"],"font size name\u0004Huge":["Огромный"],"font size name\u0004Large":["Большой"],"font size name\u0004Medium":["Средний"],"font size name\u0004Small":["Маленький"],"font size name\u0004Normal":["Обычный"],"keyboard button\u0004Enter":["Ввод"],"button label\u0004Import":["Импорт"],"button label\u0004Download":["Скачать"],"button label\u0004Embed":["Вставить"],"block title\u0004Embed":["Вставка"],"block title\u0004Classic":["Классический"],"block style\u0004Large":["Большой"],"block style\u0004Rounded":["Закругленный"],"Link edited.":["Ссылка изменена."],"Link removed.":["Ссылка удалена."],"media":["медиафайл"],"Double-check your settings before publishing.":["Дважды проверьте ваши настройки перед публикацией."],"Generating preview…":["Создание предварительного просмотра..."],"Edit or update the image":["Изменить или обновить изображение"],"Media":["Медиафайлы"],"Navigate to the nearest toolbar.":["Навигация по ближайшей панели инструментов."],"Document tools":["Инструменты документа"],"Document and block tools":["Инструменты документа и блоков"],"Embed a video from your media library or upload a new one.":["Вставьте видео из вашей медиатеки или загрузите новое."],"Insert poetry. Use special spacing formats. Or quote song lyrics.":["Вставить поэтические строфы. Можно использовать специальный формат интервалов или цитировать текст песни."],"Add white space between blocks and customize its height.":["Добавьте пространство между блоками и настройте его высоту."],"Insert additional custom elements with a WordPress shortcode.":["Вставить дополнительные пользовательские элементы с помощью шорткода."],"Create a break between ideas or sections with a horizontal separator.":["Создайте промежуток между идеями или разделами с помощью горизонтального разделителя."],"Give quoted text visual emphasis. \"In quoting others, we cite ourselves.\" — Julio Cortázar":["Визуально акцентируйте цитируемый текст. \"Цитируя других, мы цитируем себя.\" - Julio Cortázar"],"Give special visual emphasis to a quote from your text.":["Визуально акцентируйте цитату из вашего текста."],"Start with the building block of all narrative.":["Начните с создания повествовательного блока."],"Separate your content into a multi-page experience.":["Разделите содержимое на несколько страниц."],"Set media and words side-by-side for a richer layout.":["Установите мультимедиа элемент и текст по бокам от него для богатства макета."],"Media & Text settings":["Настройки мультимедиа и текста"],"Create a bulleted or numbered list.":["Создайте маркированый или нумерованый список."],"Display a list of your most recent comments.":["Покажите список самых свежих комментариев."],"Insert an image to make a visual statement.":["Добавьте изображение для визуального утверждения."],"Add custom HTML code and preview it as you edit.":["Добавьте произвольный код HTML и смотрите на результат в процессе редактирования."],"Introduce new sections and organize content to help visitors (and search engines) understand the structure of your content.":["Объявите новые разделы и организуйте содержимое для удобства посетителей (и поисковых систем) в понимании его структуры."],"Display multiple images in a rich gallery.":["Объедините несколько изображений в роскошной галерее."],"Add a link to a downloadable file.":["Добавьте ссылку на скачиваемый файл."],"Embed videos, images, tweets, audio, and other content from external sources.":["Вставить видео, изображения, твиты, аудио и другое содержимое из внешних источников."],"Resize for smaller devices":["Изменить размер для устройств с небольшим экраном"],"This embed may not preserve its aspect ratio when the browser is resized.":["Этот встроенный объект может не сохранять соотношение сторон при изменении размера окна браузера."],"This embed will preserve its aspect ratio when the browser is resized.":["Этот встроенный объект сохранит соотношение сторон при изменении размера окна браузера."],"Embed an Animoto video.":["Вставить видео Animoto."],"Embed a Vimeo video.":["Вставить видео Vimeo."],"Embed Flickr content.":["Вставить содержимое Flickr."],"Embed Spotify content.":["Вставить содержимое Spotify."],"Embed SoundCloud content.":["Вставить содержимое SoundCloud."],"Embed a WordPress post.":["Вставить запись WordPress."],"Embed an Instagram post.":["Вставить запись Instagram."],"Embed a Facebook post.":["Вставить запись Facebook."],"Embed a WordPress.tv video.":["Вставить видео WordPress.tv."],"Embed a VideoPress video.":["Вставить видео VideoPress."],"Embed a Tumblr post.":["Вставить запись Tumblr."],"Embed a TED video.":["Вставить видео TED."],"Embed Speaker Deck content.":["Вставить содержимое Speaker Deck."],"Embed a YouTube video.":["Вставить видео YouTube."],"Embed SmugMug content.":["Вставить содержимое SmugMug."],"Embed Slideshare content.":["Вставить содержимое Slideshare."],"Embed Scribd content.":["Вставить содержимое Scribd."],"Embed Screencast content.":["Вставить содержимое Screencast."],"Embed ReverbNation content.":["Вставить содержимое ReverbNation."],"Embed a Reddit thread.":["Вставить обсуждение Reddit."],"Embed Polldaddy content.":["Вставить содержимое Polldaddy."],"Embed Mixcloud content.":["Вставить содержимое Mixcloud."],"Embed a tweet.":["Вставить твит."],"Embed Meetup.com content.":["Вставить содержимое Meetup.com."],"Embed Kickstarter content.":["Вставить содержимое Kickstarter."],"Embed Issuu content.":["Вставить содержимое Issuu."],"Embed Imgur content.":["Вставить содержимое Imgur."],"Embed Hulu content.":["Вставить содержимое Hulu."],"Embed a Dailymotion video.":["Вставить видео Dailymotion."],"Embed CollegeHumor content.":["Вставить содержимое CollegeHumor."],"Embed Cloudup content.":["Вставить содержимое Cloudup."],"Add an image or video with a text overlay — great for headers.":["Добавьте изображение или видео с текстовым перекрытием — замечательно для заголовков."],"Display code snippets that respect your spacing and tabs.":["Покажите фрагменты кода с интервалами и табуляцией."],"Use the classic WordPress editor.":["Использовать классический редактор WordPress."],"Display a list of all categories.":["Показ списка всех рубрик."],"Embed a simple audio player.":["Вставить простой аудиопроигрыватель."],"noun\u0004View":["Вид"],"editor button\u0004Left to right":["Слева направо"],"Save as Pending":["Сохранить для утверждения"],"%s address":["%s адрес"],"Paste or type URL":["Вставить или ввести URL-адрес"],"Insert from URL":["Вставить с сайта"],"Block Navigator":["Навигация по блокам"],"Styles":["Стили"],"Advanced panels":["Расширенные панели"],"Document panels":["Панели документов"],"General":["Общие"],"Open the block navigation menu.":["Откроет меню навигации по блокам."],"Work without distraction":["Работа без отвлечения внимания"],"Focus on one block at a time":["Сосредоточьтесь на одном блоке"],"Access all block and document tools in a single place":["Доступ ко всем блокам и инструментам в одном месте"],"Options":["Настройки"],"(opens in a new tab)":["(откроется в новой вкладке)"],"Minutes":["Минуты"],"Hours":["Часы"],"Time":["Время"],"Year":["Год"],"Day":["День"],"December":["Декабрь"],"November":["Ноябрь"],"October":["Октябрь"],"September":["Сентябрь"],"August":["Август"],"July":["Июль"],"June":["Июнь"],"May":["Май"],"April":["Апрель"],"March":["Март"],"February":["Февраль"],"January":["Январь"],"Month":["Месяц"],"Date":["Дата"],"Go to the first (home) or last (end) day of a week.":["Перейдите в первый (home) или последний (end) день недели."],"Home/End":["Home/End"],"Home and End":["Home и End"],"Move backward (PgUp) or forward (PgDn) by one month.":["Перемещение назад (PgUp) или вперед (PgDn) на один месяц."],"PgUp/PgDn":["PgUp/PgDn"],"Page Up and Page Down":["Page Up и Page Down"],"Move backward (up) or forward (down) by one week.":["Перемещение назад (вверх) или вперед (вниз) на одну неделю."],"Up and Down Arrows":["Вверх и Вниз стрелки"],"Move backward (left) or forward (right) by one day.":["Перемещение назад (влево) или вперед (вправо) на один день."],"Left and Right Arrows":["Влево и Вправо стрелки"],"Select the date in focus.":["Выберите дату в фокусе."],"Navigating with a keyboard":["Навигация с помощью клавиатуры"],"Click the desired day to select it.":["Нажмите на нужный день, чтобы выбрать его."],"Click the right or left arrows to select other months in the past or the future.":["Нажмите стрелки вправо или влево для выбора других месяцев в прошлом или в будущем."],"Click to Select":["Нажмите, чтобы выбрать"],"Calendar Help":["Помощь по календарю"],"Use your arrow keys to change the base color. Move up to lighten the color, down to darken, left to decrease saturation, and right to increase saturation.":["Используйте клавиши со стрелками для изменения цвета. Переместите вверх - чтобы осветлить цвет, вниз - чтобы затемнить, влево - чтобы уменьшить насыщенность, и вправо - чтобы увеличить насыщенность."],"Choose a shade":["Выберите оттенок"],"Change color format":["Изменение цветового формата"],"Color value in HSL":["Значение цвета в HSL"],"Color value in RGB":["Значение цвета в RGB"],"Color value in hexadecimal":["Значение цвета в HEX-формате"],"RGB mode active":["Режим RGB активен"],"Hex color mode active":["HEX режим активен"],"Hue/saturation/lightness mode active":["HSL режим активен"],"Move the arrow left or right to change hue.":["Переместите стрелку влево или вправо, чтобы изменить оттенок."],"Hue value in degrees, from 0 to 359.":["Значение оттенка в градусах, от 0 до 359."],"Alpha value, from 0 (transparent) to 1 (fully opaque).":["Значение альфа, от 0 (прозрачный) до 1 (полностью непрозрачный)."],"Stripes":["Полосы"],"Your site doesn’t include support for this block.":["Ваш сайт не поддерживает этот блок."],"Your site doesn’t include support for the \"%s\" block. You can leave this block intact or remove it entirely.":["Ваш сайт не поддерживает \"%s\" блок. Вы можете оставить этот блок нетронутым или полностью удалить его."],"Your site doesn’t include support for the \"%s\" block. You can leave this block intact, convert its content to a Custom HTML block, or remove it entirely.":["Ваш сайт не поддерживает \"%s\" блок. Вы можете оставить этот блок нетронутым, преобразовать его содержимое в произвольный HTML-блок или полностью удалить его."],"Media area":["Область мультимедиа"],"Media & Text":["Медиа и Текст"],"Show media on right":["Показать медиа справа"],"Show media on left":["Показать медиа слева"],"Cover":["Обложка"],"Border settings":["Настройки границы"],"Medium":["Средний"],"Paste URL or type to search":["Введите URL или слово для поиска"],"Terms":["Термины"],"Your work will be published at the specified date and time.":["Ваш труд будет опубликован в указанную дату и время."],"Are you ready to schedule?":["Вы готовы запланировать?"],"Always show pre-publish checks.":["Всегда показывать проверки перед публикацией"],"Take Over":["Перехватить"],"Another user is currently working on this post, which means you cannot make changes, unless you take over.":["Другой пользователь уже редактирует эту запись. Вы хотите перехватить?"],"%s is currently working on this post, which means you cannot make changes, unless you take over.":["%s уже редактирует эту запись. Вы хотите перехватить?"],"Another user now has editing control of this post. Don’t worry, your changes up to this moment have been saved.":["В данный момент другой пользователь редактирует эту запись. Не беспокойтесь, все ваши изменения на текущий момент будут сохранены"],"%s now has editing control of this post. Don’t worry, your changes up to this moment have been saved.":["%s в данный момент редактирует эту запись. Не беспокойтесь, все ваши изменения на текущий момент будут сохранены"],"Avatar":["Аватар"],"This post is already being edited.":["Запись уже редактируется."],"Someone else has taken over this post.":["Кто-то еще перехватил эту запись."],"This block contains unexpected or invalid content.":["Этот блок имеет неожиданное или неверное содержимое."],"Resolve Block":["Исправить блок"],"Convert to HTML":["Преобразовать в HTML"],"This block can only be used once.":["Этот блок можно использовать только один раз."],"Exit code editor":["Выйти из редактора кода"],"Editing code":["Редактор кода"],"Solid color":["Сплошной цвет"],"Main color":["Основной цвет"],"HTML":["HTML"],"Write HTML…":["Пишите HTML..."],"Media settings":["Медиа настройки"],"Overlay":["Наложение"],"Insert Media":["Вставить медиафайл"],"Reusable block imported successfully!":["\"Мой блок\" импортирован успешно!"],"Invalid Reusable Block JSON file":["Невалидный JSON файл для \"Моего блока\""],"Invalid JSON file":["Недопустимый JSON-файл"],"Import from JSON":["Импорт из JSON"],"Backtick":["Кавычка"],"Period":["Точка"],"Comma":["Запятая"],"Change type of %d block":["Изменить тип %d блока","Изменить тип %d блоков","Изменить тип %d блоков"],"Current":["Текущий"],"After Conversion":["После преобразования"],"Change alignment":["Изменить выравнивание"],"Change text alignment":["Изменить выравнивание текста"],"%d block":["%d блок","%d блока","%d блоков"],"Forward-slash":["Обратный слеш"],"No archives to show.":["Нет архивов для просмотра."],"This file is empty.":["Этот файл пуст."],"Sorry, this file type is not supported here.":["К сожалению, этот тип файла здесь не поддерживается."],"Manage all reusable blocks":["Управление всеми \"Моими блоками\""],"Title":["Заголовок"],"Fullscreen mode":["Полноэкранный режим"],"Beautiful landscape":["Прекрасный пейзаж"],"Close panel":["Закрыть панель"],"Convert to Classic Block":["Конвертировать в классический блок"],"Poster image":["Постер"],"This block is deprecated. Please use the Columns block instead.":["Этот блок устарел. Вместо этого используйте блок «Столбцы»."],"Text Columns (deprecated)":["Текстовые столбцы (устарел)"],"Create":["Создать"],"Row Count":["Количество строк"],"Column Count":["Количество столбцов"],"This block is deprecated. Please use the Paragraph block instead.":["Этот блок устарел. Вместо этого используйте блок «Параграф»."],"Subheading (deprecated)":["Подзаголовок (устарел)"],"blockquote":["цитата"],"Create and save content to reuse across your site. Update the block, and the changes apply everywhere it’s used.":["Создавайте и сохраняйте контент для повторного использования на вашем сайте. Обновите блок, и изменения применяются повсюду, где он используется."],"Change the block type after adding a new paragraph.":["Изменить тип блока после добавления нового параграфа."],"Spotlight mode":["Режим подсветки"],"Tags help users and search engines navigate your site and find your content. Add a few keywords to describe your post.":["Метки помогают пользователям и поисковым системам перемещаться по вашему сайту и находить ваше содержимое. Добавьте несколько ключевых слов для описания вашей записи."],"Add tags":["Добавить метки"],"Apply the \"%1$s\" format.":["Применить формат «%1$s»."],"Your theme uses post formats to highlight different kinds of content, like images or videos. Apply a post format to see this special styling.":["В вашей теме используются форматы записей, чтобы выделять различные виды содержимого, например изображений или видео. Примените формат записи, чтобы увидеть этот особый стиль."],"Use a post format":["Использовать формат записи"],"Insert After":["Вставить после"],"Insert Before":["Вставить до"],"Move %1$d block from position %2$d down by one place":["Переместить %1$d блок с позиции %2$d вниз на одну позицию","Переместить %1$d блока с позиции %2$d вниз на одну позицию","Переместить %1$d блоков с позиции %2$d вниз на одну позицию"],"Move %1$d block from position %2$d up by one place":["Переместить %1$d блок с позиции %2$d вверх на одну позицию","Переместить %1$d блока с позиции %2$d вверх на одну позицию","Переместить %1$d блоков с позиции %2$d вверх на одну позицию"],"Move %1$s block from position %2$d right to position %3$d":["Переместить %1$s блок из позиции %2$d в позицию %3$d"],"Move %1$s block from position %2$d up to position %3$d":["Переместить блок %1$s из позиции %2$d в позицию %3$d"],"movie":["фильм"],"Insert a new block before the selected block(s).":["Вставить новый блок перед выбранным блоком."],"Remove the selected block(s).":["Удалить выбранный блок(и)."],"Duplicate the selected block(s).":["Дублировать выбранный блок(и)."],"Block shortcuts":["Блоки"],"Clear selection.":["Очистить выбор."],"Select all text when typing. Press again to select all blocks.":["Выбрать все. Нажмите еще раз, чтобы выбрать все блоки."],"Selection shortcuts":["Выбор"],"Switch between visual editor and code editor.":["Переключение между визуальным редактором и редактором кода."],"Navigate to the previous part of the editor.":["Перейти к предыдущей части редактора."],"Navigate to the next part of the editor.":["Перейти к следующей части редактора."],"Show or hide the settings sidebar.":["Показать или скрыть боковую панель настроек."],"Redo your last undo.":["Повторить последнюю отмену."],"Undo your last changes.":["Отменить свои последние изменения."],"Save your changes.":["Сохранить изменения."],"Global shortcuts":["Общие"],"Remove a link.":["Удалить ссылку."],"Convert the selected text into a link.":["Преобразовать выделенный текст в ссылку."],"Underline the selected text.":["Подчеркнуть выделенный текст."],"Make the selected text italic.":["Сделать выделенный текст курсивом."],"Make the selected text bold.":["Сделать выделенный текст жирным."],"Text formatting":["Форматирование текста"],"Insert a new block after the selected block(s).":["Вставить новый блок после выбранного блока."],"Keyboard shortcuts":["Горячие клавиши"],"Thanks for testing Gutenberg!":["Спасибо за тестирование Gutenberg!"],"Help build Gutenberg":["Помогите создавать Gutenberg"],"If you want to learn more about how to build additional blocks, or if you are interested in helping with the project, head over to the <a href=\"%s\">GitHub repository</a>.":["Если вы хотите узнать больше о том, как создавать дополнительные блоки, или если вы хотите помочь в развитии проекта, заходите в <a href=\"%s\">репозиторий GitHub</a>."],"The WordPress community":["Сообщество WordPress"],"Code is Poetry":["Код — это поэзия."],"You can build any block you like, static or dynamic, decorative or plain. Here&#8217;s a pullquote block:":["Вы можете построить любой интересующий вас блок, статический или динамический, декоративный или простой. Вот блок Выдержка:"],"Any block can opt into these alignments. The embed block has them also, and is responsive out of the box:":["Любой блок может быть выровнен. Встраиваемый блок имеет их также выравнивается и является адаптивным по умолчанию:"],"The above is a gallery with just two images. It&#8217;s an easier way to create visually appealing layouts, without having to deal with floats. You can also easily convert the gallery back to individual images again, by using the block switcher.":["Выше была галерея с двумя изображениями. Это более простой способ создания визуально привлекательных макетов. Вы также можете легко преобразовать галерею обратно в отдельные изображения, используя блок-переключатель."],"Sure, the full-wide image can be pretty big. But sometimes the image is worth it.":["Конечно, полномасштабное изображение может быть довольно большим. Но иногда это стоит того."],"Accessibility is important &mdash; don&#8217;t forget image alt attribute":["Доступность важна &mdash; не забывайте атрибут alt"],"If you combine the new <strong>wide</strong> and <strong>full-wide</strong> alignments with galleries, you can create a very media rich layout, very quickly:":["Если объединить новые выравнивания <strong>по ширине содержимого</strong> и <strong>на всю ширину</strong> с галереями, вы можете создать очень богатый медиа-макет очень быстро:"],"Media Rich":["Медиа"],"You can change the amount of columns in your galleries by dragging a slider in the block inspector in the sidebar.":["Вы можете изменить количество столбцов в своих галереях, перетащив ползунок в инспекторе блоков на боковой панели."],"Blocks can be anything you need. For instance, you may want to add a subdued quote as part of the composition of your text, or you may prefer to display a giant stylized one. All of these options are available in the inserter.":["Блоки могут быть любыми. Например, вы можете добавить цитату как часть композиции своего текста или вы можете показать гигантский стилизованный текст. Все это доступно в настройках."],"The information corresponding to the source of the quote is a separate text field, similar to captions under images, so the structure of the quote is protected even if you select, modify, or remove the source. It&#8217;s always easy to add it back.":["Информация о источнике цитаты представляет собой отдельное текстовое поле, аналогичное подписи под изображениями. Поэтому структура цитаты неизменная, даже если вы выбираете, изменяете или удаляете источник. Источник можно легко добавить в любое время."],"Matt Mullenweg, 2017":["Мэтт Мулленвег, 2017"],"The editor will endeavor to create a new page and post building experience that makes writing rich posts effortless, and has “blocks” to make it easy what today might take shortcodes, custom HTML, or “mystery meat” embed discovery.":["Редактор стремится дать новый опыт создания постов и страниц, который позволит легко создавать насыщенные посты с помощью «блоков» - вместо использующихся сейчас шорткодов, произвольных html или всевозможных махинаций со вставкой кода"],"A huge benefit of blocks is that you can edit them in place and manipulate your content directly. Instead of having fields for editing things like the source of a quote, or the text of a button, you can directly change the content. Try editing the following quote:":["Огромное преимущество блоков заключается в том, что вы можете сразу их редактировать и напрямую манипулировать своим контентом. Вместо того, чтобы изменять поля для редактирования таких вещей, как источник цитаты, или текст кнопки, вы можете напрямую изменить содержимое. Попробуйте отредактировать следующую цитату:"],"Visual Editing":["Визуальное редактирование"],"And <em>Lists</em> like this one of course :)":["И <em>списки</em>, как эти, конечно :)"],"Layout blocks, like Buttons, Hero Images, Separators, etc.":["Блоки макетов, кнопки, изображения, разделители и т.д."],"Embeds, like YouTube, Tweets, or other WordPress posts.":["Вставки, видео с YouTube, твиты или другие записи WordPress."],"Galleries":["Галереи"],"Images &amp; Videos":["Изображения и видео"],"Text &amp; Headings":["Текст и заголовки"],"Go give it a try, you may discover things WordPress can already add into your posts that you didn&#8217;t know about. Here&#8217;s a short list of what you can currently find there:":["Попробуйте, WordPress уже может добавить в ваши записи, блоки о которых вы не знали. Вот краткий список того, что вы можете найти в настоящее время:"],"Imagine everything that WordPress can do is available to you quickly and in the same place on the interface. No need to figure out HTML tags, classes, or remember complicated shortcode syntax. That&#8217;s the spirit behind the inserter—the <code>(+)</code> button you&#8217;ll see around the editor—which allows you to browse all available content blocks and add them into your post. Plugins and themes are able to register their own, opening up all sort of possibilities for rich editing and publishing.":["Представьте, что все, что может сделать WordPress, доступно вам быстро и из одного места. Нет необходимости определять HTML-теги, классы или помнить сложный синтаксис шорткодов. Кнопка <code>(+)</code>, которую вы увидите около редактора, позволяет просматривать все доступные блоки контента и добавлять их в свою запись. Плагины и темы могут регистрировать свои собственные блоки, открывая все возможности для редактирования и публикации ваших статей."],"The <em>Inserter</em> Tool":["Инструмент <em>вставки</em>"],"Try selecting and removing or editing the caption, now you don&#8217;t have to be careful about selecting the image or other text by mistake and ruining the presentation.":["Попробуйте выбрать, удалить или отредактировать заголовок. Теперь вам не нужно быть осторожным при выборе изображения или другого текста, чтобы не разрушить презентацию."],"If your theme supports it, you&#8217;ll see the \"wide\" button on the image toolbar. Give it a try.":["Если ваша тема поддерживает режим «на всю ширину», вы увидите кнопку «на всю ширину» на панели инструментов. Попробуйте."],"Handling images and media with the utmost care is a primary focus of the new editor. Hopefully, you&#8217;ll find aspects of adding captions or going full-width with your pictures much easier and robust than before.":["Основное внимание в новом редакторе уделяется обработке изображений и мультимедиа с максимальной осторожностью. Надеемся, вы найдете возможности добавления подписи изображения или перехода на полную ширину намного проще и надежнее, чем раньше."],"A Picture is Worth a Thousand Words":["Одна картинка стоит тысячи слов"],"Headings are separate blocks as well, which helps with the outline and organization of your content.":["Заголовки также являются отдельными блоками, что помогает с организацией вашего содержимого статьи."],"... like this one, which is right aligned.":["... как этот, который выровнен по правому краю."],"What you are reading now is a <strong>text block</strong> the most basic block of all. The text block has its own controls to be moved freely around the post...":["То, что вы сейчас читаете, представляет собой <strong>параграф</strong>. Самый основной блок из всех. Параграф имеет свои собственные элементы управления, которые можно свободно перемещать по записи..."],"The goal of this new editor is to make adding rich content to WordPress simple and enjoyable. This whole post is composed of <em>pieces of content</em>—somewhat similar to LEGO bricks—that you can move around and interact with. Move your cursor around and you&#8217;ll notice the different blocks light up with outlines and arrows. Press the arrows to reposition blocks quickly, without fearing about losing things in the process of copying and pasting.":["Цель нового редактора - сделать добавление контента в WordPress простым и приятным. Вся эта запись состоит из <em> фрагментов контента</em>, что похоже на LEGO-кирпичи, которые вы можете перемещать и конструировать. Перемещайте курсор, и вы заметите, что различные блоки загораются контурами и стрелками. Нажмите стрелки, чтобы быстро переместить блоки, не опасаясь потерять контент в процессе копирования и вставки."],"Of Mountains &amp; Printing Presses":["Книга гор и морей"],"Welcome to the Gutenberg Editor":["Добро пожаловать в редактор Gutenberg"],"block name\u0004More":["Тег «Далее»"],"button to expand options\u0004More":["Больше настроек"],"Are you sure you want to unschedule this post?":["Вы уверены,что хотите отменить расписание этой записи?"],"Alt text (alternative text)":["Alt (альтернативный текст)"],"Reusable Block":["Мой блок"],"The title for the object.":["Название для объекта."],"Unique identifier for the object.":["Уникальный идентификатор для объекта."],"Untitled Reusable Block":["Мой блок без названия"],"Small":["Small"],"Reusable":["Мой блок"],"Remove from Reusable blocks":["Удалить из \"Моих блоков\""],"Add to Reusable blocks":["Добавить в \"Мои блоки\""],"Keep as HTML":["Сохранить как HTML"],"Edit URL":["Редактировать URL"],"Color settings":["Настройки цвета"],"The response is not a valid JSON response.":["Ответ не является допустимым ответом JSON."],"Muted":["Приглушенный"],"Video settings":["Настройки видео"],"recent comments":["недавние комментарии"],"Latest Comments":["Последние комментарии"],"Display avatar":["Показать аватар"],"Latest comments settings":["Настройки последних комментариев"],"Number of comments":["Количество комментариев"],"Background opacity":["Непрозрачность фона"],"Auto":["Авто"],"Preload":["Предварительная загрузка"],"Audio settings":["Настройки аудио"],"Display a monthly archive of your posts.":["Показывать архивы записей за месяц."],"Archives settings":["Настройки архивов"],"https://wordpress.org/support/plugin/gutenberg":["https://wordpress.org/support/plugin/gutenberg"],"Support":["Поддержка"],"No comments to show.":["Нет комментариев для просмотра."],"%1$s on %2$s":["%1$s к %2$s"],"Select Post":["Выберите запись"],"Select Week":["Выберите неделю"],"Select Day":["Выберите день"],"Select Month":["Выберите месяц"],"Select Year":["Выберите год"],"Archives":["Архивы"],"Very dark gray":["Тёмно-серый"],"Cyan bluish gray":["Голубовато-серый"],"Very light gray":["Светло-серый"],"Vivid cyan blue":["Ярко-синий"],"Pale cyan blue":["Бледно-голубой"],"Vivid green cyan":["Ярко-зеленый"],"Light green cyan":["Светло-зеленый"],"Luminous vivid amber":["Янтарный"],"Luminous vivid orange":["Ярко-оранжевый"],"Vivid red":["Ярко-красный"],"Pale pink":["Бледно-розовый"],"Inline image":["Встроенное изображение"],"Available block types":["Доступные типы блоков"],"Transform to":["Преобразовать в"],"Remove Block":["Удалить блок"],"Open publish panel":["Открыть панель публикации"],"Dots":["Точки"],"Wide Line":["Широкая линия"],"Large":["Большой"],"Show download button":["Показать кнопку загрузки"],"Download button settings":["Настройки кнопки загрузки"],"Link to":["Ссылка на"],"Text link settings":["Настройки текстовой ссылки"],"download":["скачать"],"pdf":["pdf"],"document":["документ"],"Copy URL":["Копировать URL"],"Write file name…":["Впишите имя файла ..."],"File":["Файл"],"A single column within a columns block.":["Одна колонка в блоке колонок."],"Column":["Столбец"],"Outline":["Контур"],"Loop":["Зациклить"],"Autoplay":["Автозапуск"],"Playback controls":["Элементы управления воспроизведением"],"Close dialog":["Закрыть окно"],"Sorry, this file type is not permitted for security reasons.":["Извините, этот тип файла недопустим по соображениям безопасности."],"Disable tips":["Отключить советы"],"Got it":["Понятно"],"See next tip":["Следующий совет"],"When you’re ready, submit your work for review, and an Editor will be able to approve it for you.":["Когда вы будете готовы, отправьте свою работу на проверку, и редактор сможет ее одобрить."],"Are you ready to submit for review?":["Вы готовы отправить на рассмотрение?"],"Remove image":["Удалить изображение"],"Invalid term ID.":["Неверный ID элемента."],"The ID for the parent of the object.":["ID родителя объекта."],"Error while uploading file %s to the media library.":["Ошибка загрузки файла %s в медиатеку."],"This file exceeds the maximum upload size for this site.":["Размер файла превышает максимальный для этого сайта."],"View the autosave":["Посмотреть автосохранение"],"There is an autosave of this post that is more recent than the version below.":["Существует более поздняя версия этой записи, чем версия ниже."],"Autosaving":["Автосохранение"],"Enter URL here…":["Введите URL здесь..."],"Pin to toolbar":["Прикрепить к панели инструментов"],"Unpin from toolbar":["Открепить от панели инструментов"],"Insert a table — perfect for sharing charts and data.":["Вставить таблицу — отличный выбор для графиков и данных."],"Fixed width table cells":["Ячейки таблицы фиксированной ширины"],"Table settings":["Настройки таблицы"],"Add text that respects your spacing and tabs, and also allows styling.":["Добавьте текст, который соответствует вашим интервалам и вкладкам, а также позволяет стилизовать."],"Display a list of your most recent posts.":["Выводит список ваших последних записей."],"Add a block that displays content pulled from other sites, like Twitter, Instagram or YouTube.":["Добавляет блок, который выводит содержимое с других сайтов, таких как Twitter, Instagram или YouTube."],"Add a block that displays content in multiple columns, then add whatever content blocks you’d like.":["Добавьте блок, отображающий содержимое в нескольких столбцах, а затем добавьте любые блоки, которые вы хотите."],"Error loading block: %s":["Ошибка загрузки блока: %s"],"Unknown error":["Неизвестная ошибка"],"Embed Handler":["Вставить обработчик"],"term\u0004Remove %s":["Удалить %s"],"Height in pixels":["Высота в пикселях"],"Spacer settings":["Настройки интервала"],"Spacer":["Интервал"],"Toggle to show a large initial letter.":["Сделать начальную букву большой."],"Showing large initial letter.":["Отображение большой начальной буквы."],"Name:":["Имя:"],"%1$s (%2$s of %3$s)":["%1$s (%2$s из %3$s)"],"Remove item":["Удалить пункт"],"Color code: %s":["Цвет: %s"],"Skip to the selected block":["Перейти к выбранному блоку"],"Schedule…":["Запланировать..."],"Show Block Settings":["Показать параметры блока"],"Hide Block Settings":["Скрыть параметры блока"],"Block settings closed":["Настройки блока закрыты"],"Close plugin":["Закрыть плагин"],"Link settings":["Настройки ссылок"],"Unlink":["Убрать ссылку"],"Page break":["Разрыв страницы"],"pagination":["пагинация"],"next page":["следущая страница"],"Image Size":["Размер изображения"],"Height":["Высота"],"Width":["Ширина"],"Image dimensions":["Размеры изображения"],"Thumbnails are not cropped.":["Миниатюры не обрезаны."],"Thumbnails are cropped to align.":["Миниатюры обрезаются для выравнивания."],"Media Library":["Библиотека файлов"],"Advanced":["Дополнительно"],"Add item":["Добавить элемент"],"Reset the template":["Сбросить шаблон"],"Keep it as is":["Оставить без изменений"],"The content of your post doesn’t match the template assigned to your post type.":["Содержимое не соответствует шаблону, назначенному этому типу записи."],"Resetting the template may result in loss of content, do you want to continue?":["Сброс шаблона может привести к потере содержимого, хотите продолжить?"],"Document Statistics":["Статистика документа"],"is now scheduled. It will go live on":["запланирована и будет опубликована"],"Scheduled":["Запланирован"],"Scheduling…":["Планирование..."],"Code editor selected":["Выбран редактор кода"],"Visual editor selected":["Выбран визуальный редактор"],"Plugins":["Плагины"],"Custom Size":["Произвольный"],"Layout elements":["Элементы разметки"],"term\u0004%s removed":["%s удален"],"term\u0004%s added":["%s добавлен"],"imperative verb\u0004Preview":["Предпросмотр"],"Block deleted.":["Блок удален."],"Block updated.":["Блок обновлен."],"Block created.":["Блок создан."],"Trashing failed":["Удаление в корзину не удалось"],"Updating failed.":["Ошибка обновления."],"Scheduling failed.":["Не удалось запланировать."],"Publishing failed.":["Ошибка публикации."],"View post":["Просмотреть запись"],"You have unsaved changes. If you proceed, they will be lost.":["У вас есть несохраненные изменения. Если вы продолжите, они будут потеряны."],"Document Outline":["Структура документа"],"Paragraphs":["Параграфы"],"Headings":["Заголовки"],"Words":["Слова"],"Content structure":["Структура статьи"],"Public":["Открыто"],"Protected with a password you choose. Only those with the password can view this post.":["Защищена паролем, который вы укажете. Запись смогут посмотреть только те, у кого есть пароль."],"Password Protected":["Защищено паролем"],"Only visible to site admins and editors.":["Видна только администраторам и редакторам."],"Private":["Личное"],"Visible to everyone.":["Видна всем."],"Post Visibility":["Видимость записи"],"Would you like to privately publish this post now?":["Вы хотите опубликовать запись как личную?"],"Use a secure password":["Впишите надежный пароль"],"Create password":["Создать пароль"],"Move to Trash":["Переместить в корзину"],"Parent Term":["Родительский термин"],"Parent Category":["Родительская рубрика"],"Add new term":["Добавить новый термин"],"Add new category":["Добавить новую рубрику"],"Term":["Термин"],"Tag":["Метка"],"Add new Term":["Добавить новый термин"],"Add new tag":["Добавить новую метку"],"Switch to draft":["Переключиться на черновик"],"Are you sure you want to unpublish this post?":["Вы уверены, что хотите отменить публикацию записи?"],"Immediately":["Немедленно"],"Save Draft":["Сохранить"],"Saving":["Сохранение"],"Publish:":["Опубликована:"],"Visibility:":["Видимость:"],"Are you ready to publish?":["Вы готовы опубликовать?"],"Copy Link":["Копировать ссылку"],"What’s next?":["Что дальше?"],"is now live.":["опубликована."],"Published":["Опубликовано"],"Schedule":["Запланировать"],"Update":["Обновить"],"Submit for Review":["Отправить на рассмотрение"],"Updating…":["Обновление..."],"Publishing…":["Публикация..."],"Allow pingbacks & trackbacks":["Разрешить уведомления и обратные ссылки"],"Pending review":["На утверждении"],"%d Revision":["%d редакция","%d редакции","%d редакций"],"Suggestion:":["Предложение:"],"Post Format":["Формат записи"],"Chat":["Чат"],"Status":["Статус"],"Standard":["Стандартный"],"Aside":["Заметка"],"Featured image":["Изображение записи"],"Set featured image":["Задать изображение"],"Learn more about manual excerpts":["Подробнее об отрывках"],"Write an excerpt (optional)":["Написать отрывок (необязательно)"],"Allow comments":["Разрешить комментарии"],"Template:":["Шаблон:"],"no parent":["без родителя"],"no title":["без заголовка"],"Order":["Порядок сортировки"],"No blocks found.":["Блоков не найдено."],"%d result found.":["%d результат найден.","%d результата найдено.","%d результатов найдено."],"Saved":["Сохранено"],"Embeds":["Вставки"],"Blocks":["Блоки"],"Search for a block":["Поиск блоков"],"Add block":["Добавить блок"],"Copy Error":["Скопировать текст ошибки"],"Copy Post Text":["Скопировать текст записи"],"Attempt Recovery":["Попытаться восстановить"],"The editor has encountered an unexpected error.":["Произошла непредвиденная ошибка."],"Undo":["Отменить"],"Redo":["Повторить"],"(Multiple H1 headings are not recommended)":["(Не рекомендуется использовать более одного тега H1)"],"(Your theme may already use a H1 for the post title)":["(Ваша тема уже может использовать тег H1 для заголовка записи)"],"(Incorrect heading level)":["(Некорректный уровень заголовка)"],"(Empty heading)":["(Без заголовка)"],"Are you sure you want to delete this Reusable Block?\n\nIt will be permanently removed from all posts and pages that use it.":["Вы уверены, что хотите удалить этот общий блок?\nВаши действия приведут к удалению его из всех записей и страниц."],"Convert to Regular Block":["Преобразовать в обычный блок"],"More options":["Еще настройки"],"Edit visually":["Редактировать визуально"],"Duplicate":["Дублировать"],"Blocks cannot be moved down as they are already at the bottom":["Блоки не могут быть перемещены вниз, так как они уже находятся в самом низу"],"Blocks cannot be moved up as they are already at the top":["Блоки не могут быть перемещены вверх, так как они уже находятся сверху"],"Block %1$s is at the beginning of the content and can’t be moved right":["Блок %1$s находится в самом верху и не может быть перемещён"],"Block %1$s is at the end of the content and can’t be moved right":["Блок %1$s находится в самом низу и не может быть перемещён правильно"],"Block %s is the only block, and cannot be moved":["Блок %s является единственным блоком и не может быть перемещен"],"Move down":["Переместить вниз"],"Move up":["Переместить вверх"],"Edit as HTML":["Редактировать как HTML"],"Convert to Blocks":["Преобразовать в блоки"],"Block: %s":["Блок: %s"],"This block has encountered an error and cannot be previewed.":["Этот блок содержит ошибку и не может быть просмотрен."],"No block selected.":["Блок не выбран."],"Transform into:":["Преобразовать в:"],"Remove":["Удалить"],"Find original":["Найти оригинал"],"Copy all content":["Скопировать всё содержимое"],"Copied!":["Скопировано!"],"Additional settings are now available in the Editor block settings sidebar":["Дополнительные настройки теперь доступны на боковой панели расширенных настроек"],"Visibility":["Видимость"],"Status & visibility":["Статус и видимость"],"Page attributes":["Атрибуты страницы"],"Block":["Блок"],"Document":["Документ"],"Close settings":["Закрыть настройки"],"Tools":["Инструменты"],"Editor":["Редактор"],"Code editor":["Редактор кода"],"Visual editor":["Визуальный редактор"],"Settings":["Настройки"],"Reset":["Сбросить"],"Dismiss this notice":["Закрыть это уведомление"],"Item removed.":["Элемент удален."],"Item added.":["Элемент добавлен."],"Drop files to upload":["Перетащите файлы сюда"],"PM":["ПП"],"AM":["ДП"],"An unknown error occurred.":["Произошла неизвестная ошибка."],"No results.":["Нет результатов."],"%d result found, use up and down arrow keys to navigate.":["Найден %d результат. Используйте стрелки на клавиатуре для навигации.","Найдено %d результата. Используйте стрелки на клавиатуре для навигации.","Найдено %d результатов. Используйте стрелки на клавиатуре для навигации."],"(no title)":["(без названия)"],"URL":["URL"],"Submit":["Отправить"],"Close":["Закрыть"],"Insert link":["Вставить ссылку"],"Edit link":["Изменить ссылку"],"Link":["Ссылка"],"Strikethrough":["Зачеркнутый"],"Italic":["Курсив"],"Bold":["Жирный"],"Remove link":["Удалить ссылку"],"Number of items":["Количество элементов"],"All":["Все"],"Category":["Рубрика"],"Z → A":["Я &rarr; А"],"A → Z":["А &rarr; Я"],"Oldest to newest":["От старого к новому"],"Newest to oldest":["От нового к старому"],"Order by":["Сортировать по"],"Select":["Выбрать"],"Select or Upload Media":["Выбрать или загрузить"],"Video":["Видео"],"Write…":["Напишите..."],"poetry":["поэзия"],"Verse":["Стих"],"New Column":["Новый столбец"],"Delete Column":["Удалить столбец"],"Add Column After":["Добавить столбец после"],"Add Column Before":["Добавить столбец до"],"Delete Row":["Удалить строку"],"Add Row After":["Добавить строку после"],"Add Row Before":["Добавить строку до"],"Edit table":["Редактировать таблицу"],"Table":["Таблица"],"Write subheading…":["Введите подзаголовок..."],"Write shortcode here…":["Введите шорткод здесь..."],"Shortcode":["Шорткод"],"divider":["разделитель"],"horizontal-line":["горизонтальная-линия"],"Separator":["Разделитель"],"Quote":["Цитата"],"Write citation…":["Введите цитату..."],"Write quote…":["Введите цитату..."],"Pullquote":["Выдержка"],"Write preformatted text…":["Напишите предварительно отформатированный текст..."],"Preformatted":["Форматированный"],"text":["текст"],"Paragraph":["Параграф"],"Font size":["Размер шрифта"],"Drop cap":["Буквица"],"Text settings":["Настройки текста"],"Read more":["Подробнее"],"Write list…":["Составить список..."],"numbered list":["нумерованный список"],"ordered list":["упорядоченный список"],"bullet list":["маркированный список"],"Indent list item":["Добавить отступ к элементам списка"],"Outdent list item":["Убрать отступ у элементов списка"],"Convert to ordered list":["Преобразовать в нумерованный список"],"Convert to unordered list":["Преобразовать в маркированный список"],"List":["Список"],"recent posts":["последние записи"],"No posts found.":["Записей не найдено."],"Latest Posts":["Последние записи"],"Display post date":["Отображать дату публикации"],"Grid view":["В виде сетки"],"List view":["В виде списка"],"photo":["фотография"],"Image settings":["Настройки изображения"],"Image":["Изображение"],"Preview":["Просмотреть"],"embed":["вставка"],"Custom HTML":["HTML-код"],"subtitle":["подзаголовок"],"title":["заголовок"],"Heading":["Заголовок"],"Write heading…":["Введите заголовок..."],"Heading %d":["Заголовок %s"],"Level":["Уровень"],"Heading settings":["Настройки заголовка"],"photos":["фотографии"],"images":["изображения"],"None":["Нет"],"Media File":["Медиафайл"],"Attachment Page":["Страница вложения"],"Crop images":["Обрезка изображений"],"Gallery settings":["Настройки галереи"],"Gallery":["Галерея"],"Classic":["Классический"],"video":["видео"],"audio":["аудио"],"music":["музыка"],"image":["изображение"],"blog":["блог"],"post":["запись"],"Embedded content from %s":["Вставленное содержимое с %s"],"Enter URL to embed here…":["Укажите URL для вставки..."],"%s URL":["%s URL"],"Embedding…":["Вставка..."],"Write title…":["Введите заголовок..."],"Fixed background":["Фиксированный фон"],"Edit image":["Редактировать изображение"],"Columns":["Колонки"],"Experiments":["Экспериментальная функция"],"Code":["Код"],"Write code…":["Введите код..."],"Categories":["Рубрики"],"Show hierarchy":["Показать иерархию"],"Show post counts":["Показать кол-во записей"],"Display as dropdown":["Показать выпадающим списком"],"Categories settings":["Настройки рубрик"],"Add text…":["Добавить текст…"],"Button":["Кнопка"],"Apply":["Применить"],"Text Color":["Цвет текста"],"Background Color":["Цвет фона"],"Block has been deleted or is unavailable.":["Блок удален или недоступен."],"Reusable blocks":["Мои блоки"],"Cancel":["Отмена"],"Edit":["Изменить"],"Write caption…":["Напишите подпись..."],"Use URL":["Использовать URL"],"Audio":["Аудио"],"Upload":["Загрузить"],"Additional CSS class(es)":["Дополнительный класс(ы) CSS"],"HTML anchor":["HTML якорь"],"This color combination may be hard for people to read. Try using a brighter background color and/or a darker text color.":["Это сочетание цветов может затруднить чтение. Попробуйте использовать более яркий цвет фона и/или более темный цвет текста."],"This color combination may be hard for people to read. Try using a darker background color and/or a brighter text color.":["Это сочетание цветов может затруднить чтение. Попробуйте использовать более темный цвет фона и/или более яркий цвет текста."],"Clear":["Сброс"],"Custom color picker":["Произвольный выбор цвета"],"Color: %s":["Цвет: %s"],"Full width":["Во всю ширину"],"Wide width":["По ширине содержимого"],"Widgets":["Виджеты"],"Formatting":["Форматирование"],"Common blocks":["Основные блоки"],"Align right":["По правому краю"],"Align center":["По центру"],"Align left":["По левому краю"],"Printing since 1440. This is the development plugin for the new block editor in core.":["Печатаем с 1440 года. Это разработка плагина для нового редактора блоков в ядре."],"Add title":["Добавить заголовок"],"Gutenberg development mode requires files to be built. Run <code>npm install</code> to install dependencies, <code>npm run build</code> to build the files or <code>npm run dev</code> to build the files and watch for changes. Read the <a href=\"https://github.com/WordPress/gutenberg/blob/master/docs/contributors/getting-started.md\">contributing</a> file for more information.":["Режим разработки Gutenberg требует компоновки файлов. Запустите <code>npm install</code> для установки зависимостей, <code>npm run build</code> для компоновки файлов или <code>npm run dev</code> для их компоновки и отслеживания изменений. Для более детальной информации ознакомьтесь с файлом <a href=\"https://github.com/WordPress/gutenberg/blob/master/docs/contributors/getting-started.md\">об участии</a>."],"Author":["Автор"],"Slug":["Слаг (slug)"],"Comment":["Комментарий"],"Discussion":["Обсуждение"],"Custom fields":["Произвольные поля"],"Excerpt":["Отрывок"],"Publish":["Опубликовать"],"Metadata":["Метаданные"],"Save":["Сохранить"],"Documentation":["Документация"],"Select Category":["Выберите рубрику"],"Invalid post type.":["Неверный тип записи."],"(Untitled)":["(Без названия)"],"Gutenberg requires WordPress %s or later to function properly. Please upgrade WordPress before activating Gutenberg.":["Gutenberg требуется WordPress %s или выше, для корректной работы. Пожалуйста, обновите WordPress перед активацией Gutenberg."],"Gutenberg Team":["Команда Gutenberg"],"https://github.com/WordPress/gutenberg":["https://github.com/WordPress/gutenberg"],"Gutenberg":["Gutenberg"],"Demo":["Демо"],"%s ago":["%s назад"],"Block style name must be a string.":["Имена типов блоков должны быть строкой."]}