{
  "name": "RNReactNativeRecyclerviewList",
  "version": "1.0.0",
  "summary": "RNReactNativeRecyclerviewList",
  "description": "RNReactNativeRecyclerviewList",
  "homepage": "",
  "license": "MIT",
  "authors": {
    "author": "author@domain.cn"
  },
  "platforms": {
    "ios": "7.0"
  },
  "source": {
    "git": "https://github.com/author/RNReactNativeRecyclerviewList.git",
    "tag": "master"
  },
  "source_files": "RNReactNativeRecyclerviewList/**/*.{h,m}",
  "requires_arc": true,
  "dependencies": {
    "React": [

    ]
  }
}
